MANIFEST.in
README.md
setup.py
javcore.egg-info/PKG-INFO
javcore.egg-info/SOURCES.txt
javcore.egg-info/dependency_links.txt
javcore.egg-info/entry_points.txt
javcore.egg-info/requires.txt
javcore.egg-info/top_level.txt
src/common/__init__.py
src/data/__init__.py
src/db/__init__.py
src/db/bj.py
src/db/import_dao.py
src/db/jav.py
src/db/jav2.py
src/db/maker.py
src/db/mysql_base.py
src/db/replace_info.py
src/site/__init__.py
src/site/fc2.py
src/site/mgs.py
src/site/wiki.py
src/tool/__init__.py
src/tool/p_number.py
test/test_common.py