Metadata-Version: 2.1
Name: javcore
Version: 0.1.8
Summary: Scraping Jav Core
Home-page: https://github.com/pypa/sampleproject
Author: Juichi Hirao
Author-email: hirao@theta-inc.co.jp
License: UNKNOWN
Project-URL: Bug Reports, https://github.com/pypa/sampleproject/issues
Project-URL: Funding, https://donate.pypi.org
Project-URL: Say Thanks!, http://saythanks.io/to/example
Project-URL: Source, https://github.com/pypa/sampleproject/
Keywords: sample setuptools development
Platform: UNKNOWN
Classifier: Development Status :: 3 - Alpha
Classifier: Intended Audience :: Developers
Classifier: Topic :: Software Development :: Build Tools
Classifier: License :: OSI Approved :: MIT License
Classifier: Programming Language :: Python :: 3.6
Classifier: Programming Language :: Python :: 3.7
Provides-Extra: test
Provides-Extra: dev
